MANIFEST.in
README
setup.py
PyAlgoTrade.egg-info/PKG-INFO
PyAlgoTrade.egg-info/SOURCES.txt
PyAlgoTrade.egg-info/dependency_links.txt
PyAlgoTrade.egg-info/requires.txt
PyAlgoTrade.egg-info/top_level.txt
googleappengine/app/app.yaml
googleappengine/app/index.yaml
googleappengine/app/queue.yaml
googleappengine/app/strategyexecutor.py
googleappengine/app/usertasks.py
googleappengine/app/chanchero/__init__.py
googleappengine/app/chanchero/config.py
googleappengine/app/chanchero/mastertaskhandler.py
googleappengine/app/chanchero/resulttaskhandler.py
googleappengine/app/chanchero/tasks.py
googleappengine/app/chanchero/workertaskhandler.py
googleappengine/app/common/__init__.py
googleappengine/app/common/cls.py
googleappengine/app/common/forms.py
googleappengine/app/common/logger.py
googleappengine/app/common/parameters.py
googleappengine/app/common/timer.py
googleappengine/app/common/utils.py
googleappengine/app/pages/__init__.py
googleappengine/app/pages/home.py
googleappengine/app/pages/strategy.py
googleappengine/app/persistence/__init__.py
googleappengine/app/resources/rw_common/version.txt
googleappengine/app/resources/rw_common/themes/realmacsoftware06/colourtag-theme-default.css
googleappengine/app/resources/rw_common/themes/realmacsoftware06/handheld.css
googleappengine/app/resources/rw_common/themes/realmacsoftware06/ie6.css
googleappengine/app/resources/rw_common/themes/realmacsoftware06/ie7.css
googleappengine/app/resources/rw_common/themes/realmacsoftware06/javascript.js
googleappengine/app/resources/rw_common/themes/realmacsoftware06/print.css
googleappengine/app/resources/rw_common/themes/realmacsoftware06/styles.css
googleappengine/app/resources/rw_common/themes/realmacsoftware06/css/sidebar/hide.css
googleappengine/app/resources/rw_common/themes/realmacsoftware06/css/sidebar/left.css
googleappengine/app/resources/rw_common/themes/realmacsoftware06/css/sidebar/right.css
googleappengine/app/resources/rw_common/themes/realmacsoftware06/css/width/1000.css
googleappengine/app/resources/rw_common/themes/realmacsoftware06/css/width/600.css
googleappengine/app/resources/rw_common/themes/realmacsoftware06/css/width/700.css
