Metadata-Version: 1.0
Name: PyAlgoTrade
Version: 0.14
Summary: Python Algorithmic Trading
Home-page: http://gbeced.github.io/pyalgotrade/
Author: Gabriel Martin Becedillas Ruiz
Author-email: pyalgotrade@gmail.com
License: UNKNOWN
Download-URL: http://sourceforge.net/projects/pyalgotrade/files/0.14/PyAlgoTrade-0.14.tar.gz/download
Platform: UNKNOWN
